<annotation>
	<folder>Green</folder>
	<filename>left0068.jpg</filename>
	<path>E:\projects\python\Traffic-Light-Classification\data\simulator_dataset_rgb\Green\left0068.jpg</path>
	<source>
		<database>Unknown</database>
	</source>
	<size>
		<width>800</width>
		<height>600</height>
		<depth>3</depth>
	</size>
	<segmented>0</segmented>
	<object>
		<name>Green</name>
		<pose>Unspecified</pose>
		<truncated>0</truncated>
		<difficult>0</difficult>
		<bndbox>
			<xmin>258</xmin>
			<ymin>442</ymin>
			<xmax>286</xmax>
			<ymax>504</ymax>
		</bndbox>
	</object>
	<object>
		<name>Green</name>
		<pose>Unspecified</pose>
		<truncated>0</truncated>
		<difficult>0</difficult>
		<bndbox>
			<xmin>141</xmin>
			<ymin>439</ymin>
			<xmax>168</xmax>
			<ymax>501</ymax>
		</bndbox>
	</object>
	<object>
		<name>Green</name>
		<pose>Unspecified</pose>
		<truncated>0</truncated>
		<difficult>0</difficult>
		<bndbox>
			<xmin>21</xmin>
			<ymin>435</ymin>
			<xmax>48</xmax>
			<ymax>498</ymax>
		</bndbox>
	</object>
</annotation>
