<annotation>
	<folder>Red</folder>
	<filename>left0325.jpg</filename>
	<path>E:\projects\python\Traffic-Light-Classification\data\simulator_dataset_rgb\Red\left0325.jpg</path>
	<source>
		<database>Unknown</database>
	</source>
	<size>
		<width>800</width>
		<height>600</height>
		<depth>3</depth>
	</size>
	<segmented>0</segmented>
	<object>
		<name>Red</name>
		<pose>Unspecified</pose>
		<truncated>0</truncated>
		<difficult>0</difficult>
		<bndbox>
			<xmin>272</xmin>
			<ymin>361</ymin>
			<xmax>314</xmax>
			<ymax>454</ymax>
		</bndbox>
	</object>
	<object>
		<name>Red</name>
		<pose>Unspecified</pose>
		<truncated>0</truncated>
		<difficult>0</difficult>
		<bndbox>
			<xmin>449</xmin>
			<ymin>363</ymin>
			<xmax>490</xmax>
			<ymax>456</ymax>
		</bndbox>
	</object>
	<object>
		<name>Red</name>
		<pose>Unspecified</pose>
		<truncated>0</truncated>
		<difficult>0</difficult>
		<bndbox>
			<xmin>625</xmin>
			<ymin>364</ymin>
			<xmax>671</xmax>
			<ymax>457</ymax>
		</bndbox>
	</object>
</annotation>
