<annotation>
	<folder>Yellow</folder>
	<filename>left0405.jpg</filename>
	<path>E:\projects\python\Traffic-Light-Classification\data\simulator_dataset_rgb\Yellow\left0405.jpg</path>
	<source>
		<database>Unknown</database>
	</source>
	<size>
		<width>800</width>
		<height>600</height>
		<depth>3</depth>
	</size>
	<segmented>0</segmented>
	<object>
		<name>Yellow</name>
		<pose>Unspecified</pose>
		<truncated>0</truncated>
		<difficult>0</difficult>
		<bndbox>
			<xmin>185</xmin>
			<ymin>326</ymin>
			<xmax>236</xmax>
			<ymax>434</ymax>
		</bndbox>
	</object>
	<object>
		<name>Yellow</name>
		<pose>Unspecified</pose>
		<truncated>0</truncated>
		<difficult>0</difficult>
		<bndbox>
			<xmin>389</xmin>
			<ymin>328</ymin>
			<xmax>437</xmax>
			<ymax>435</ymax>
		</bndbox>
	</object>
	<object>
		<name>Yellow</name>
		<pose>Unspecified</pose>
		<truncated>0</truncated>
		<difficult>0</difficult>
		<bndbox>
			<xmin>593</xmin>
			<ymin>330</ymin>
			<xmax>645</xmax>
			<ymax>440</ymax>
		</bndbox>
	</object>
</annotation>
